myws/__init__.py
myws-0.1.0.dist-info/LICENSE
myws-0.1.0.dist-info/METADATA
myws-0.1.0.dist-info/WHEEL
myws-0.1.0.dist-info/top_level.txt
myws-0.1.0.dist-info/RECORD
